{
  "gp": {
    "note": "suggested corner phases as lap fractions (start/apex/end). Heuristic from severity; review and edit. Not authoritative.",
    "corners": {
      "1": {
        "number": 1,
        "code": "1",
        "scale": 2,
        "scale_label": "Slow",
        "brakes": true,
        "complex": null,
        "apex": 0.0663,
        "start": 0.01236,
        "end": 0.10526
      },
      "2": {
        "number": 2,
        "code": "2",
        "scale": 6,
        "scale_label": "Kink",
        "brakes": false,
        "complex": null,
        "apex": 0.1559,
        "start": 0.1559,
        "end": 0.1559
      },
      "3": {
        "number": 3,
        "code": "3",
        "scale": 3,
        "scale_label": "Medium",
        "brakes": true,
        "complex": null,
        "apex": 0.2318,
        "start": 0.19584,
        "end": 0.24871
      },
      "4": {
        "number": 4,
        "code": "4",
        "scale": 3,
        "scale_label": "Medium",
        "brakes": true,
        "complex": null,
        "apex": 0.269,
        "start": 0.24871,
        "end": 0.29532
      },
      "5": {
        "number": 5,
        "code": "5",
        "scale": 2,
        "scale_label": "Slow",
        "brakes": true,
        "complex": null,
        "apex": 0.3427,
        "start": 0.29532,
        "end": 0.35604
      },
      "6": {
        "number": 6,
        "code": "6",
        "scale": 1,
        "scale_label": "Hairpin",
        "brakes": true,
        "complex": null,
        "apex": 0.3817,
        "start": 0.35604,
        "end": 0.39606
      },
      "7": {
        "number": 7,
        "code": "7",
        "scale": 3,
        "scale_label": "Medium",
        "brakes": true,
        "complex": null,
        "apex": 0.4062,
        "start": 0.39606,
        "end": 0.41588
      },
      "8": {
        "number": 8,
        "code": "8",
        "scale": 2,
        "scale_label": "Slow",
        "brakes": true,
        "complex": null,
        "apex": 0.4333,
        "start": 0.41588,
        "end": 0.47226
      },
      "9": {
        "number": 9,
        "code": "9",
        "scale": 5,
        "scale_label": "Very fast",
        "brakes": true,
        "complex": null,
        "apex": 0.5267,
        "start": 0.51621,
        "end": 0.54019
      },
      "10": {
        "number": 10,
        "code": "10",
        "scale": 2,
        "scale_label": "Slow",
        "brakes": true,
        "complex": "Nouvelle Chicane",
        "apex": 0.6322,
        "start": 0.57826,
        "end": 0.63451
      },
      "11": {
        "number": 11,
        "code": "11",
        "scale": 2,
        "scale_label": "Slow",
        "brakes": true,
        "complex": "Nouvelle Chicane",
        "apex": 0.6377,
        "start": 0.63451,
        "end": 0.67666
      },
      "12": {
        "number": 12,
        "code": "12",
        "scale": 3,
        "scale_label": "Medium",
        "brakes": true,
        "complex": null,
        "apex": 0.7176,
        "start": 0.68164,
        "end": 0.73842
      },
      "13": {
        "number": 13,
        "code": "13",
        "scale": 3,
        "scale_label": "Medium",
        "brakes": true,
        "complex": "Swimming Pool",
        "apex": 0.7634,
        "start": 0.73842,
        "end": 0.76811
      },
      "14": {
        "number": 14,
        "code": "14",
        "scale": 2,
        "scale_label": "Slow",
        "brakes": true,
        "complex": "Swimming Pool",
        "apex": 0.7766,
        "start": 0.76811,
        "end": 0.79124
      },
      "15": {
        "number": 15,
        "code": "15",
        "scale": 2,
        "scale_label": "Slow",
        "brakes": true,
        "complex": "Swimming Pool",
        "apex": 0.8115,
        "start": 0.79124,
        "end": 0.81784
      },
      "16": {
        "number": 16,
        "code": "16",
        "scale": 3,
        "scale_label": "Medium",
        "brakes": true,
        "complex": "Swimming Pool",
        "apex": 0.8237,
        "start": 0.81784,
        "end": 0.84064
      },
      "17": {
        "number": 17,
        "code": "17",
        "scale": 1,
        "scale_label": "Hairpin",
        "brakes": true,
        "complex": null,
        "apex": 0.883,
        "start": 0.84064,
        "end": 0.89801
      },
      "18": {
        "number": 18,
        "code": "18",
        "scale": 3,
        "scale_label": "Medium",
        "brakes": true,
        "complex": null,
        "apex": 0.9086,
        "start": 0.89801,
        "end": 0.91325
      },
      "19": {
        "number": 19,
        "code": "19",
        "scale": 4,
        "scale_label": "Fast",
        "brakes": true,
        "complex": null,
        "apex": 0.9165,
        "start": 0.91325,
        "end": 0.93748
      }
    }
  }
}
